compile_dcm2bids_config.py
compile_dcm2bids_config-1.4.3.dist-info/entry_points.txt
compile_dcm2bids_config-1.4.3.dist-info/LICENSE
compile_dcm2bids_config-1.4.3.dist-info/WHEEL
compile_dcm2bids_config-1.4.3.dist-info/METADATA
compile_dcm2bids_config-1.4.3.dist-info/RECORD
