Metadata-Version: 2.1
Name: compile-dcm2bids-config
Version: 1.4.3
Summary: Compile Dcm2Bids configuration files into a single config file.
Home-page: https://github.com/andrewrosss/compile-dcm2bids-config
License: MIT
Keywords: bids,dcm2bids,config,configuration,tool
Author: Andrew Ross
Author-email: andrew.ross.mail@gmail.com
Requires-Python: >=3.6.2,<4.0
Classifier: Development Status :: 4 - Beta
Classifier: Environment :: Console
Classifier: Intended Audience :: Developers
Classifier: License :: OSI Approved :: MIT License
Classifier: Operating System :: OS Independent
Classifier: Programming Language :: Python :: 3
Classifier: Programming Language :: Python :: 3.0
Classifier: Programming Language :: Python :: 3.10
Classifier: Programming Language :: Python :: 3.7
Classifier: Programming Language :: Python :: 3.8
Classifier: Programming Language :: Python :: 3.9
Classifier: Topic :: Software Development :: Libraries :: Python Modules
Classifier: Topic :: Utilities
Classifier: Typing :: Typed
Provides-Extra: yaml
Requires-Dist: PyYAML (>=6.0,<7.0); extra == "yaml"
Requires-Dist: dataclasses (>=0.6); python_version < "3.7"
Project-URL: Documentation, https://github.com/andrewrosss/compile-dcm2bids-config
Project-URL: Repository, https://github.com/andrewrosss/compile-dcm2bids-config
